{
  "PieceName": "puzzle_01345",
  "Edges": [
    {
      "Index": 0,
      "Connection": []
    },
    {
      "Index": 1,
      "Connection": [
        "puzzle_00952, 1, 1.211",
        "puzzle_01517, 2, 2.147",
        "puzzle_00655, 2, 2.302",
        "puzzle_00988, 1, 2.848",
        "puzzle_00809, 2, 3.417",
        "puzzle_00724, 0, 3.432",
        "puzzle_01804, 0, 3.459",
        "puzzle_00695, 2, 3.473",
        "puzzle_01385, 1, 4.088",
        "puzzle_01884, 2, 4.408"
      ]
    },
    {
      "Index": 2,
      "Connection": [
        "puzzle_00043, 3, 1.076",
        "puzzle_00426, 1, 1.141",
        "puzzle_00558, 1, 1.178",
        "puzzle_01529, 1, 1.261",
        "puzzle_00234, 1, 1.310",
        "puzzle_01950, 3, 1.353",
        "puzzle_00026, 1, 1.421",
        "puzzle_00838, 3, 1.434",
        "puzzle_01578, 3, 1.459",
        "puzzle_01311, 2, 1.529",
        "puzzle_00701, 3, 1.544",
        "puzzle_00015, 1, 1.547",
        "puzzle_01504, 1, 1.575",
        "puzzle_00280, 1, 1.600",
        "puzzle_00168, 1, 1.605",
        "puzzle_00740, 1, 1.606",
        "puzzle_00265, 3, 1.616",
        "puzzle_01763, 3, 1.618",
        "puzzle_00735, 1, 1.647",
        "puzzle_00437, 1, 1.650",
        "puzzle_01047, 1, 1.652",
        "puzzle_01983, 3, 1.661",
        "puzzle_01127, 3, 1.664",
        "puzzle_01928, 3, 1.672",
        "puzzle_01664, 3, 1.684",
        "puzzle_01393, 3, 1.692",
        "puzzle_01032, 3, 1.708",
        "puzzle_01583, 3, 1.770",
        "puzzle_00238, 3, 1.793",
        "puzzle_00690, 1, 1.801",
        "puzzle_01514, 1, 1.801",
        "puzzle_01787, 3, 1.802",
        "puzzle_01270, 3, 1.833",
        "puzzle_01236, 0, 1.843",
        "puzzle_01220, 3, 1.862",
        "puzzle_00943, 3, 1.865",
        "puzzle_01215, 1, 1.865",
        "puzzle_00239, 1, 1.874",
        "puzzle_00880, 1, 1.882",
        "puzzle_01241, 1, 1.897",
        "puzzle_01210, 1, 1.897",
        "puzzle_01131, 1, 1.901",
        "puzzle_01469, 1, 1.903",
        "puzzle_00826, 3, 1.916",
        "puzzle_00757, 1, 1.916",
        "puzzle_00487, 3, 1.917",
        "puzzle_00771, 3, 1.917",
        "puzzle_00837, 3, 1.933",
        "puzzle_01440, 1, 1.950",
        "puzzle_00628, 1, 1.955",
        "puzzle_00444, 3, 1.955",
        "puzzle_00259, 1, 1.967",
        "puzzle_00993, 1, 1.970",
        "puzzle_01590, 3, 1.976",
        "puzzle_00848, 3, 1.978",
        "puzzle_00075, 3, 1.985",
        "puzzle_00490, 1, 1.990",
        "puzzle_00987, 1, 1.998",
        "puzzle_00424, 1, 2.015",
        "puzzle_00167, 0, 2.023",
        "puzzle_00551, 1, 2.024",
        "puzzle_01316, 1, 2.024",
        "puzzle_01121, 0, 2.027",
        "puzzle_00870, 3, 2.038",
        "puzzle_00396, 3, 2.045",
        "puzzle_00405, 1, 2.050",
        "puzzle_00053, 3, 2.075",
        "puzzle_00843, 1, 2.078",
        "puzzle_00020, 3, 2.079",
        "puzzle_01461, 1, 2.088",
        "puzzle_00528, 3, 2.089",
        "puzzle_00223, 3, 2.089",
        "puzzle_00565, 1, 2.102",
        "puzzle_00465, 1, 2.113",
        "puzzle_00216, 3, 2.114",
        "puzzle_00527, 1, 2.117",
        "puzzle_00464, 1, 2.124",
        "puzzle_00357, 1, 2.153",
        "puzzle_00022, 3, 2.161",
        "puzzle_01754, 1, 2.172",
        "puzzle_01042, 3, 2.174",
        "puzzle_01257, 1, 2.197",
        "puzzle_01253, 1, 2.208",
        "puzzle_01399, 1, 2.211",
        "puzzle_01026, 1, 2.214",
        "puzzle_00275, 1, 2.215",
        "puzzle_00277, 1, 2.222",
        "puzzle_01896, 1, 2.231",
        "puzzle_01812, 1, 2.250",
        "puzzle_00271, 1, 2.252",
        "puzzle_00343, 0, 2.255",
        "puzzle_01685, 1, 2.260",
        "puzzle_00152, 1, 2.262",
        "puzzle_01678, 1, 2.267",
        "puzzle_01585, 3, 2.268",
        "puzzle_01822, 1, 2.272",
        "puzzle_01944, 1, 2.273",
        "puzzle_00274, 3, 2.278",
        "puzzle_01428, 3, 2.294",
        "puzzle_00511, 1, 2.295",
        "puzzle_01200, 3, 2.299",
        "puzzle_01423, 1, 2.303",
        "puzzle_00023, 0, 2.321",
        "puzzle_00404, 1, 2.334",
        "puzzle_01802, 1, 2.337",
        "puzzle_01278, 1, 2.352",
        "puzzle_01171, 1, 2.354",
        "puzzle_01681, 3, 2.355",
        "puzzle_01108, 1, 2.356",
        "puzzle_00463, 3, 2.357",
        "puzzle_00579, 1, 2.359",
        "puzzle_00804, 1, 2.363",
        "puzzle_00933, 1, 2.365",
        "puzzle_01147, 1, 2.370",
        "puzzle_00722, 3, 2.379",
        "puzzle_00295, 1, 2.384",
        "puzzle_00810, 1, 2.395",
        "puzzle_01809, 3, 2.395",
        "puzzle_00481, 3, 2.401",
        "puzzle_00781, 1, 2.404",
        "puzzle_01437, 3, 2.408",
        "puzzle_01943, 1, 2.409",
        "puzzle_00893, 1, 2.413",
        "puzzle_01515, 3, 2.414",
        "puzzle_01933, 1, 2.420",
        "puzzle_01905, 3, 2.421",
        "puzzle_00827, 3, 2.427",
        "puzzle_00900, 1, 2.434",
        "puzzle_00505, 1, 2.437",
        "puzzle_01226, 3, 2.441",
        "puzzle_01187, 3, 2.441",
        "puzzle_01756, 3, 2.447",
        "puzzle_00948, 1, 2.460",
        "puzzle_01790, 3, 2.463",
        "puzzle_00981, 3, 2.466",
        "puzzle_00319, 1, 2.467",
        "puzzle_01894, 1, 2.467",
        "puzzle_00792, 3, 2.470",
        "puzzle_00725, 1, 2.480",
        "puzzle_00117, 3, 2.488",
        "puzzle_01846, 3, 2.511",
        "puzzle_00438, 1, 2.511",
        "puzzle_00050, 1, 2.515",
        "puzzle_00524, 1, 2.515",
        "puzzle_01878, 1, 2.521",
        "puzzle_00534, 1, 2.522",
        "puzzle_00584, 1, 2.535",
        "puzzle_01367, 1, 2.548",
        "puzzle_00608, 3, 2.550",
        "puzzle_00973, 1, 2.551",
        "puzzle_00065, 3, 2.553",
        "puzzle_01118, 1, 2.565",
        "puzzle_00339, 1, 2.569",
        "puzzle_01392, 1, 2.572",
        "puzzle_01057, 3, 2.573",
        "puzzle_00149, 1, 2.582",
        "puzzle_01242, 1, 2.585",
        "puzzle_00875, 1, 2.596",
        "puzzle_01356, 0, 2.608",
        "puzzle_00784, 3, 2.629",
        "puzzle_00350, 0, 2.652",
        "puzzle_00369, 1, 2.665",
        "puzzle_01346, 3, 2.667",
        "puzzle_00675, 1, 2.668",
        "puzzle_01952, 3, 2.675",
        "puzzle_01934, 1, 2.677",
        "puzzle_00403, 3, 2.688",
        "puzzle_00232, 0, 2.688",
        "puzzle_00615, 1, 2.693",
        "puzzle_00500, 1, 2.696",
        "puzzle_00241, 3, 2.714",
        "puzzle_00324, 1, 2.717",
        "puzzle_00632, 1, 2.725",
        "puzzle_00824, 3, 2.729",
        "puzzle_01321, 1, 2.729",
        "puzzle_00217, 3, 2.735",
        "puzzle_01320, 3, 2.739",
        "puzzle_00744, 1, 2.740",
        "puzzle_00320, 3, 2.741",
        "puzzle_01082, 3, 2.745",
        "puzzle_00563, 1, 2.751",
        "puzzle_01036, 1, 2.762",
        "puzzle_01347, 3, 2.774",
        "puzzle_01094, 1, 2.779",
        "puzzle_01925, 3, 2.793",
        "puzzle_01953, 1, 2.795",
        "puzzle_00739, 3, 2.797",
        "puzzle_00473, 2, 2.803",
        "puzzle_01339, 3, 2.803",
        "puzzle_01757, 1, 2.817",
        "puzzle_01960, 1, 2.822",
        "puzzle_00589, 3, 2.831",
        "puzzle_01001, 3, 2.859",
        "puzzle_01390, 1, 2.860",
        "puzzle_00745, 1, 2.868",
        "puzzle_00897, 3, 2.872",
        "puzzle_01875, 1, 2.881",
        "puzzle_01751, 1, 2.883",
        "puzzle_01038, 3, 2.884",
        "puzzle_00029, 3, 2.891",
        "puzzle_00866, 1, 2.897",
        "puzzle_01565, 3, 2.900",
        "puzzle_01908, 1, 2.910",
        "puzzle_01219, 1, 2.916",
        "puzzle_01949, 1, 2.919",
        "puzzle_01354, 1, 2.925",
        "puzzle_01628, 3, 2.938",
        "puzzle_01627, 3, 2.940",
        "puzzle_00646, 3, 2.950",
        "puzzle_00329, 1, 2.951",
        "puzzle_01255, 3, 2.952",
        "puzzle_01237, 3, 2.958",
        "puzzle_01708, 3, 2.964",
        "puzzle_01543, 3, 2.969",
        "puzzle_00411, 1, 2.972",
        "puzzle_01830, 1, 2.982",
        "puzzle_00679, 1, 2.988",
        "puzzle_00997, 3, 2.993",
        "puzzle_01109, 1, 2.999",
        "puzzle_00351, 3, 3.001",
        "puzzle_00666, 1, 3.012",
        "puzzle_01008, 1, 3.013",
        "puzzle_00322, 1, 3.014",
        "puzzle_01371, 3, 3.015",
        "puzzle_00454, 1, 3.022",
        "puzzle_01679, 1, 3.035",
        "puzzle_01405, 1, 3.035",
        "puzzle_00108, 1, 3.041",
        "puzzle_00449, 3, 3.050",
        "puzzle_01690, 3, 3.055",
        "puzzle_00705, 0, 3.055",
        "puzzle_01615, 1, 3.059",
        "puzzle_00670, 3, 3.068",
        "puzzle_01376, 1, 3.079",
        "puzzle_00031, 1, 3.094",
        "puzzle_00163, 2, 3.099",
        "puzzle_00625, 1, 3.101",
        "puzzle_00716, 1, 3.101",
        "puzzle_00884, 1, 3.120",
        "puzzle_00540, 3, 3.136",
        "puzzle_01462, 3, 3.138",
        "puzzle_01295, 1, 3.141",
        "puzzle_00903, 3, 3.143",
        "puzzle_00645, 3, 3.160",
        "puzzle_00869, 3, 3.165",
        "puzzle_00048, 3, 3.168",
        "puzzle_01599, 3, 3.170",
        "puzzle_00988, 3, 3.180",
        "puzzle_01956, 3, 3.182",
        "puzzle_01417, 3, 3.189",
        "puzzle_00392, 1, 3.192",
        "puzzle_01524, 1, 3.209",
        "puzzle_00922, 1, 3.211",
        "puzzle_01667, 3, 3.217",
        "puzzle_01630, 1, 3.223",
        "puzzle_00521, 1, 3.226",
        "puzzle_00058, 1, 3.226",
        "puzzle_00365, 3, 3.239",
        "puzzle_00302, 3, 3.243",
        "puzzle_00498, 1, 3.245",
        "puzzle_01833, 3, 3.247",
        "puzzle_00832, 3, 3.254",
        "puzzle_01519, 1, 3.267",
        "puzzle_00025, 3, 3.272",
        "puzzle_01134, 3, 3.275",
        "puzzle_01893, 1, 3.288",
        "puzzle_01884, 1, 3.294",
        "puzzle_01386, 3, 3.298",
        "puzzle_00190, 1, 3.307",
        "puzzle_01473, 1, 3.309",
        "puzzle_01889, 3, 3.316",
        "puzzle_01976, 0, 3.320",
        "puzzle_00047, 3, 3.334",
        "puzzle_01298, 3, 3.342",
        "puzzle_00060, 3, 3.350",
        "puzzle_00375, 3, 3.362",
        "puzzle_00743, 1, 3.364",
        "puzzle_00434, 1, 3.378",
        "puzzle_01798, 1, 3.385",
        "puzzle_01688, 1, 3.401",
        "puzzle_01644, 3, 3.405",
        "puzzle_00214, 3, 3.406",
        "puzzle_01492, 3, 3.407",
        "puzzle_00056, 3, 3.408",
        "puzzle_01841, 1, 3.421",
        "puzzle_00553, 1, 3.428",
        "puzzle_01139, 1, 3.429",
        "puzzle_00736, 3, 3.429",
        "puzzle_00932, 3, 3.429",
        "puzzle_01695, 3, 3.430",
        "puzzle_00825, 3, 3.434",
        "puzzle_00854, 3, 3.438",
        "puzzle_00361, 3, 3.444",
        "puzzle_00355, 1, 3.456",
        "puzzle_00911, 3, 3.458",
        "puzzle_00261, 3, 3.470",
        "puzzle_01217, 1, 3.484",
        "puzzle_00562, 3, 3.488",
        "puzzle_01913, 1, 3.500",
        "puzzle_01080, 3, 3.521",
        "puzzle_00618, 3, 3.530",
        "puzzle_01516, 1, 3.531",
        "puzzle_01168, 1, 3.537",
        "puzzle_00812, 1, 3.542",
        "puzzle_01864, 3, 3.551",
        "puzzle_01478, 3, 3.553",
        "puzzle_01511, 3, 3.553",
        "puzzle_01098, 3, 3.560",
        "puzzle_00682, 3, 3.562",
        "puzzle_01609, 3, 3.572",
        "puzzle_00446, 1, 3.577",
        "puzzle_01394, 3, 3.584",
        "puzzle_01289, 1, 3.584",
        "puzzle_01304, 3, 3.656",
        "puzzle_00243, 3, 3.662",
        "puzzle_00017, 3, 3.663",
        "puzzle_00140, 1, 3.664",
        "puzzle_01794, 1, 3.667",
        "puzzle_01505, 3, 3.679",
        "puzzle_01232, 3, 3.683",
        "puzzle_01883, 1, 3.685",
        "puzzle_01653, 1, 3.686",
        "puzzle_01797, 3, 3.693",
        "puzzle_01363, 1, 3.696",
        "puzzle_00111, 3, 3.715",
        "puzzle_00364, 3, 3.719",
        "puzzle_00680, 1, 3.723",
        "puzzle_00260, 1, 3.727",
        "puzzle_01873, 3, 3.731",
        "puzzle_00135, 1, 3.735",
        "puzzle_00835, 1, 3.756",
        "puzzle_01164, 1, 3.758",
        "puzzle_01126, 1, 3.771",
        "puzzle_00928, 1, 3.772",
        "puzzle_00691, 1, 3.774",
        "puzzle_00938, 3, 3.791",
        "puzzle_01831, 3, 3.797",
        "puzzle_00617, 1, 3.802",
        "puzzle_01863, 1, 3.808",
        "puzzle_00564, 1, 3.809",
        "puzzle_00231, 3, 3.818",
        "puzzle_00709, 1, 3.823",
        "puzzle_00248, 3, 3.823",
        "puzzle_01920, 0, 3.824",
        "puzzle_00853, 3, 3.849",
        "puzzle_00582, 3, 3.850",
        "puzzle_01317, 3, 3.856",
        "puzzle_01180, 1, 3.856",
        "puzzle_00917, 3, 3.872",
        "puzzle_00962, 3, 3.873",
        "puzzle_01986, 1, 3.922",
        "puzzle_00915, 3, 3.942",
        "puzzle_00269, 1, 3.953",
        "puzzle_00281, 1, 3.954",
        "puzzle_00839, 1, 3.956",
        "puzzle_00759, 3, 3.964",
        "puzzle_00861, 1, 3.985",
        "puzzle_01418, 3, 3.989",
        "puzzle_00447, 3, 3.996",
        "puzzle_01463, 1, 3.999",
        "puzzle_01734, 1, 4.011",
        "puzzle_01932, 3, 4.014",
        "puzzle_01597, 3, 4.020",
        "puzzle_00596, 3, 4.020",
        "puzzle_01623, 3, 4.026",
        "puzzle_00414, 3, 4.040",
        "puzzle_00389, 3, 4.070",
        "puzzle_00099, 1, 4.101",
        "puzzle_01855, 1, 4.110",
        "puzzle_00967, 1, 4.122",
        "puzzle_01795, 1, 4.147",
        "puzzle_00266, 1, 4.153",
        "puzzle_01309, 3, 4.179",
        "puzzle_01811, 3, 4.185",
        "puzzle_00685, 3, 4.197",
        "puzzle_00573, 2, 4.207",
        "puzzle_00952, 3, 4.215",
        "puzzle_00909, 1, 4.215",
        "puzzle_01508, 1, 4.233",
        "puzzle_00975, 3, 4.235",
        "puzzle_00536, 1, 4.236",
        "puzzle_00493, 3, 4.248",
        "puzzle_00046, 0, 4.269",
        "puzzle_00317, 1, 4.279",
        "puzzle_00304, 3, 4.292",
        "puzzle_01221, 1, 4.293",
        "puzzle_00024, 3, 4.298",
        "puzzle_00703, 3, 4.311",
        "puzzle_01373, 3, 4.319",
        "puzzle_01245, 3, 4.324",
        "puzzle_01369, 1, 4.330",
        "puzzle_01665, 3, 4.344",
        "puzzle_01535, 3, 4.347",
        "puzzle_00569, 2, 4.353",
        "puzzle_00762, 3, 4.358",
        "puzzle_01089, 1, 4.364",
        "puzzle_01557, 3, 4.367",
        "puzzle_00676, 1, 4.384",
        "puzzle_01771, 1, 4.396",
        "puzzle_01223, 1, 4.400",
        "puzzle_00687, 1, 4.404",
        "puzzle_01735, 3, 4.425",
        "puzzle_00477, 1, 4.447",
        "puzzle_00122, 3, 4.450",
        "puzzle_01939, 1, 4.461",
        "puzzle_01963, 3, 4.467",
        "puzzle_01377, 3, 4.486",
        "puzzle_00045, 3, 4.496",
        "puzzle_00381, 3, 4.518",
        "puzzle_00037, 1, 4.528",
        "puzzle_01331, 1, 4.541",
        "puzzle_01541, 3, 4.550",
        "puzzle_00407, 3, 4.552",
        "puzzle_00019, 1, 4.559",
        "puzzle_00591, 3, 4.575",
        "puzzle_00659, 1, 4.611",
        "puzzle_00883, 2, 4.635",
        "puzzle_00182, 0, 4.638",
        "puzzle_00514, 1, 4.641",
        "puzzle_01874, 3, 4.642",
        "puzzle_00624, 1, 4.644",
        "puzzle_01877, 1, 4.649",
        "puzzle_01430, 1, 4.676",
        "puzzle_01330, 3, 4.689",
        "puzzle_01106, 1, 4.692",
        "puzzle_01710, 3, 4.700",
        "puzzle_00613, 1, 4.707",
        "puzzle_01431, 1, 4.709",
        "puzzle_01261, 3, 4.716",
        "puzzle_00018, 3, 4.727",
        "puzzle_01396, 3, 4.744",
        "puzzle_00181, 3, 4.750",
        "puzzle_00089, 1, 4.757",
        "puzzle_00642, 1, 4.757",
        "puzzle_00177, 3, 4.782",
        "puzzle_00923, 1, 4.790",
        "puzzle_01300, 3, 4.827",
        "puzzle_00052, 1, 4.828",
        "puzzle_00844, 1, 4.829",
        "puzzle_01160, 1, 4.837",
        "puzzle_00341, 3, 4.839",
        "puzzle_01869, 3, 4.839",
        "puzzle_00079, 3, 4.857",
        "puzzle_00610, 3, 4.877",
        "puzzle_00004, 3, 4.897",
        "puzzle_00179, 3, 4.915",
        "puzzle_01954, 3, 4.930",
        "puzzle_01433, 1, 4.941",
        "puzzle_00336, 1, 4.943",
        "puzzle_01922, 3, 4.950",
        "puzzle_01530, 3, 4.957",
        "puzzle_01446, 3, 4.959",
        "puzzle_00732, 1, 4.961",
        "puzzle_01283, 1, 4.963",
        "puzzle_01544, 1, 4.969",
        "puzzle_01235, 1, 4.975",
        "puzzle_01591, 1, 4.984",
        "puzzle_00696, 1, 4.991"
      ]
    },
    {
      "Index": 3,
      "Connection": []
    }
  ]
}