{
  "PieceName": "puzzle_00207",
  "Edges": [
    {
      "Index": 0,
      "Connection": [
        "puzzle_01617, 1, 1.329",
        "puzzle_01863, 3, 1.715",
        "puzzle_01830, 0, 1.927",
        "puzzle_00598, 1, 2.064",
        "puzzle_01125, 3, 2.068",
        "puzzle_01507, 3, 2.119",
        "puzzle_01326, 3, 2.127",
        "puzzle_01744, 3, 2.458",
        "puzzle_00798, 1, 2.509",
        "puzzle_00839, 3, 2.517",
        "puzzle_00672, 3, 2.543",
        "puzzle_01882, 0, 2.613",
        "puzzle_00208, 3, 2.742",
        "puzzle_01538, 3, 2.775",
        "puzzle_01463, 3, 2.853",
        "puzzle_00477, 3, 2.880",
        "puzzle_00547, 3, 2.934",
        "puzzle_00610, 3, 2.990",
        "puzzle_00013, 1, 3.054",
        "puzzle_01619, 3, 3.182",
        "puzzle_00591, 1, 3.202",
        "puzzle_00624, 1, 3.277",
        "puzzle_01166, 3, 3.381",
        "puzzle_01430, 3, 3.442",
        "puzzle_01558, 3, 3.469",
        "puzzle_00659, 1, 3.492",
        "puzzle_01986, 3, 3.499",
        "puzzle_01229, 0, 3.506",
        "puzzle_00878, 3, 3.555",
        "puzzle_01916, 3, 3.566",
        "puzzle_00336, 3, 3.617",
        "puzzle_00349, 3, 3.635",
        "puzzle_01954, 3, 3.690",
        "puzzle_01309, 1, 3.749",
        "puzzle_01026, 3, 3.795",
        "puzzle_01341, 1, 3.798",
        "puzzle_01597, 3, 3.858",
        "puzzle_00676, 3, 3.926",
        "puzzle_01642, 1, 3.927",
        "puzzle_00229, 3, 3.959",
        "puzzle_00632, 0, 3.993",
        "puzzle_01665, 1, 3.996",
        "puzzle_01144, 3, 4.005",
        "puzzle_01441, 3, 4.010",
        "puzzle_00140, 3, 4.036",
        "puzzle_00962, 3, 4.097",
        "puzzle_00268, 1, 4.113",
        "puzzle_01369, 0, 4.139",
        "puzzle_00260, 1, 4.192",
        "puzzle_01516, 3, 4.199",
        "puzzle_01183, 1, 4.219",
        "puzzle_00511, 3, 4.230",
        "puzzle_00278, 3, 4.258",
        "puzzle_00465, 3, 4.272",
        "puzzle_00534, 3, 4.328",
        "puzzle_01645, 1, 4.371",
        "puzzle_01137, 3, 4.387",
        "puzzle_00562, 3, 4.390",
        "puzzle_01633, 3, 4.402",
        "puzzle_01484, 1, 4.434",
        "puzzle_01815, 3, 4.454",
        "puzzle_00392, 3, 4.469",
        "puzzle_01097, 3, 4.563",
        "puzzle_01591, 1, 4.587",
        "puzzle_00022, 1, 4.615",
        "puzzle_01029, 3, 4.637",
        "puzzle_00087, 1, 4.640",
        "puzzle_01848, 3, 4.683",
        "puzzle_00190, 3, 4.689",
        "puzzle_00861, 1, 4.706",
        "puzzle_00330, 1, 4.717",
        "puzzle_00017, 3, 4.741",
        "puzzle_01722, 3, 4.777",
        "puzzle_00407, 1, 4.788",
        "puzzle_01976, 3, 4.793",
        "puzzle_01242, 3, 4.805",
        "puzzle_00517, 1, 4.810",
        "puzzle_01794, 3, 4.826",
        "puzzle_01092, 2, 4.837",
        "puzzle_00256, 3, 4.856",
        "puzzle_01482, 1, 4.879",
        "puzzle_00685, 3, 4.892",
        "puzzle_01261, 3, 4.922",
        "puzzle_01386, 1, 4.926",
        "puzzle_01164, 1, 4.930",
        "puzzle_00687, 3, 4.936",
        "puzzle_01889, 1, 4.957",
        "puzzle_00815, 3, 4.963",
        "puzzle_00666, 1, 4.994",
        "puzzle_01223, 3, 4.999"
      ]
    },
    {
      "Index": 1,
      "Connection": [
        "puzzle_00987, 2, 1.249",
        "puzzle_01958, 0, 1.982",
        "puzzle_00890, 0, 2.001",
        "puzzle_01776, 0, 2.104",
        "puzzle_00387, 0, 2.142",
        "puzzle_01247, 0, 2.296",
        "puzzle_00312, 2, 2.493",
        "puzzle_00268, 0, 2.666",
        "puzzle_01871, 2, 2.714",
        "puzzle_01191, 0, 2.817",
        "puzzle_01619, 0, 2.824",
        "puzzle_00414, 2, 2.828",
        "puzzle_01943, 2, 2.838",
        "puzzle_01793, 0, 2.840",
        "puzzle_01444, 0, 2.845",
        "puzzle_00336, 2, 2.907",
        "puzzle_01116, 0, 2.921",
        "puzzle_00703, 0, 2.959",
        "puzzle_01408, 2, 2.978",
        "puzzle_00372, 2, 3.012",
        "puzzle_00526, 2, 3.097",
        "puzzle_00320, 2, 3.190",
        "puzzle_00343, 2, 3.199",
        "puzzle_01797, 2, 3.203",
        "puzzle_01330, 2, 3.207",
        "puzzle_01861, 0, 3.209",
        "puzzle_01725, 0, 3.235",
        "puzzle_01807, 2, 3.240",
        "puzzle_01262, 3, 3.274",
        "puzzle_01139, 0, 3.284",
        "puzzle_01954, 2, 3.304",
        "puzzle_00568, 0, 3.334",
        "puzzle_01511, 0, 3.347",
        "puzzle_00438, 0, 3.414",
        "puzzle_01993, 2, 3.424",
        "puzzle_01944, 0, 3.473",
        "puzzle_01787, 0, 3.477",
        "puzzle_00621, 0, 3.502",
        "puzzle_01841, 0, 3.535",
        "puzzle_01305, 2, 3.543",
        "puzzle_00745, 0, 3.638",
        "puzzle_01998, 2, 3.640",
        "puzzle_00331, 0, 3.668",
        "puzzle_01828, 2, 3.677",
        "puzzle_00418, 0, 3.700",
        "puzzle_01771, 2, 3.701",
        "puzzle_00645, 0, 3.765",
        "puzzle_01311, 0, 3.820",
        "puzzle_01400, 2, 3.833",
        "puzzle_00771, 0, 3.921",
        "puzzle_00880, 0, 3.936",
        "puzzle_00992, 0, 3.971",
        "puzzle_01818, 2, 3.974",
        "puzzle_01755, 0, 3.994",
        "puzzle_00993, 0, 4.008",
        "puzzle_01326, 0, 4.016",
        "puzzle_00554, 0, 4.031",
        "puzzle_00455, 1, 4.045",
        "puzzle_00591, 2, 4.049",
        "puzzle_00463, 0, 4.049",
        "puzzle_01869, 0, 4.082",
        "puzzle_00739, 2, 4.145",
        "puzzle_01124, 2, 4.199",
        "puzzle_01409, 1, 4.230",
        "puzzle_01765, 2, 4.252",
        "puzzle_01126, 0, 4.273",
        "puzzle_01528, 2, 4.295",
        "puzzle_00757, 0, 4.353",
        "puzzle_00266, 0, 4.380",
        "puzzle_01812, 0, 4.381",
        "puzzle_00517, 0, 4.403",
        "puzzle_00429, 2, 4.419",
        "puzzle_00382, 1, 4.422",
        "puzzle_01036, 0, 4.440",
        "puzzle_01853, 2, 4.442",
        "puzzle_01253, 2, 4.452",
        "puzzle_00899, 2, 4.479",
        "puzzle_00825, 2, 4.520",
        "puzzle_00732, 0, 4.534",
        "puzzle_00784, 0, 4.535",
        "puzzle_00884, 0, 4.553",
        "puzzle_00304, 2, 4.556",
        "puzzle_01848, 0, 4.563",
        "puzzle_00975, 0, 4.567",
        "puzzle_01407, 0, 4.571",
        "puzzle_01701, 2, 4.572",
        "puzzle_01594, 0, 4.581",
        "puzzle_00216, 0, 4.590",
        "puzzle_01734, 2, 4.608",
        "puzzle_00983, 0, 4.608",
        "puzzle_01646, 0, 4.624",
        "puzzle_01189, 0, 4.627",
        "puzzle_01555, 2, 4.627",
        "puzzle_00878, 2, 4.628",
        "puzzle_00447, 0, 4.629",
        "puzzle_01505, 2, 4.642",
        "puzzle_00055, 2, 4.663",
        "puzzle_01544, 0, 4.667",
        "puzzle_01026, 2, 4.671",
        "puzzle_00625, 0, 4.676",
        "puzzle_01188, 2, 4.681",
        "puzzle_01160, 2, 4.707",
        "puzzle_00423, 0, 4.712",
        "puzzle_01668, 0, 4.715",
        "puzzle_00533, 0, 4.718",
        "puzzle_01748, 0, 4.719",
        "puzzle_00839, 0, 4.729",
        "puzzle_00484, 2, 4.730",
        "puzzle_01519, 2, 4.731",
        "puzzle_00002, 0, 4.732",
        "puzzle_00231, 0, 4.734",
        "puzzle_01895, 0, 4.743",
        "puzzle_01066, 0, 4.753",
        "puzzle_01386, 0, 4.756",
        "puzzle_00864, 0, 4.763",
        "puzzle_01712, 0, 4.772",
        "puzzle_01390, 2, 4.774",
        "puzzle_00804, 2, 4.783",
        "puzzle_00407, 0, 4.784",
        "puzzle_00440, 2, 4.807",
        "puzzle_00453, 2, 4.810",
        "puzzle_00412, 2, 4.813",
        "puzzle_01214, 0, 4.822",
        "puzzle_01371, 2, 4.849",
        "puzzle_00083, 2, 4.859",
        "puzzle_01751, 0, 4.870",
        "puzzle_01168, 0, 4.873",
        "puzzle_01455, 0, 4.880",
        "puzzle_01916, 0, 4.880",
        "puzzle_00399, 0, 4.896",
        "puzzle_01430, 0, 4.898",
        "puzzle_00397, 0, 4.912",
        "puzzle_00606, 1, 4.923",
        "puzzle_01338, 2, 4.924",
        "puzzle_00710, 2, 4.927",
        "puzzle_01855, 2, 4.935",
        "puzzle_00712, 0, 4.960",
        "puzzle_01373, 2, 4.967",
        "puzzle_01445, 0, 4.981",
        "puzzle_01661, 3, 4.984",
        "puzzle_00722, 2, 4.991",
        "puzzle_00280, 2, 4.999"
      ]
    },
    {
      "Index": 2,
      "Connection": [
        "puzzle_01423, 1, 1.122",
        "puzzle_00223, 1, 1.217",
        "puzzle_01134, 3, 1.313",
        "puzzle_01492, 3, 1.339",
        "puzzle_01094, 1, 1.358",
        "puzzle_00563, 1, 1.361",
        "puzzle_01893, 1, 1.361",
        "puzzle_00866, 1, 1.460",
        "puzzle_00739, 3, 1.460",
        "puzzle_01516, 1, 1.470",
        "puzzle_01012, 3, 1.503",
        "puzzle_01354, 1, 1.540",
        "puzzle_01461, 1, 1.546",
        "puzzle_01220, 1, 1.585",
        "puzzle_00473, 2, 1.607",
        "puzzle_01960, 1, 1.620",
        "puzzle_01285, 1, 1.635",
        "puzzle_01131, 1, 1.636",
        "puzzle_01787, 3, 1.644",
        "puzzle_01026, 1, 1.650",
        "puzzle_00540, 3, 1.661",
        "puzzle_00838, 1, 1.661",
        "puzzle_00534, 1, 1.662",
        "puzzle_01440, 1, 1.715",
        "puzzle_01304, 3, 1.737",
        "puzzle_00329, 1, 1.744",
        "puzzle_01873, 3, 1.788",
        "puzzle_00690, 3, 1.799",
        "puzzle_00135, 1, 1.800",
        "puzzle_01871, 1, 1.801",
        "puzzle_00438, 1, 1.803",
        "puzzle_00812, 1, 1.818",
        "puzzle_01894, 1, 1.819",
        "puzzle_00564, 1, 1.824",
        "puzzle_01841, 1, 1.845",
        "puzzle_00670, 3, 1.847",
        "puzzle_00320, 3, 1.858",
        "puzzle_00675, 1, 1.865",
        "puzzle_00804, 1, 1.869",
        "puzzle_00190, 1, 1.881",
        "puzzle_00536, 3, 1.882",
        "puzzle_01215, 1, 1.886",
        "puzzle_00837, 3, 1.890",
        "puzzle_01858, 3, 1.898",
        "puzzle_01347, 3, 1.899",
        "puzzle_00710, 1, 1.909",
        "puzzle_00281, 1, 1.909",
        "puzzle_00357, 3, 1.912",
        "puzzle_00521, 1, 1.915",
        "puzzle_01171, 3, 1.945",
        "puzzle_01200, 3, 1.947",
        "puzzle_00020, 3, 1.959",
        "puzzle_00893, 1, 1.964",
        "puzzle_00745, 1, 1.972",
        "puzzle_01373, 3, 1.975",
        "puzzle_00797, 1, 1.982",
        "puzzle_00266, 1, 1.984",
        "puzzle_01417, 3, 1.990",
        "puzzle_00411, 1, 2.008",
        "puzzle_00260, 2, 2.013",
        "puzzle_01623, 3, 2.014",
        "puzzle_00465, 1, 2.015",
        "puzzle_00897, 3, 2.028",
        "puzzle_00498, 1, 2.028",
        "puzzle_00676, 1, 2.030",
        "puzzle_00141, 1, 2.034",
        "puzzle_00248, 3, 2.070",
        "puzzle_00182, 0, 2.073",
        "puzzle_00317, 1, 2.075",
        "puzzle_00680, 1, 2.076",
        "puzzle_01089, 3, 2.087",
        "puzzle_01952, 3, 2.091",
        "puzzle_00792, 3, 2.095",
        "puzzle_00050, 3, 2.099",
        "puzzle_00880, 1, 2.099",
        "puzzle_00824, 3, 2.103",
        "puzzle_00591, 3, 2.103",
        "puzzle_00274, 3, 2.107",
        "puzzle_01515, 3, 2.109",
        "puzzle_01627, 3, 2.111",
        "puzzle_00047, 3, 2.112",
        "puzzle_01356, 0, 2.121",
        "puzzle_01317, 3, 2.124",
        "puzzle_01688, 1, 2.130",
        "puzzle_00265, 1, 2.143",
        "puzzle_01690, 3, 2.145",
        "puzzle_01763, 3, 2.146",
        "puzzle_00493, 3, 2.158",
        "puzzle_00853, 3, 2.162",
        "puzzle_01036, 1, 2.171",
        "puzzle_00533, 3, 2.176",
        "puzzle_01665, 3, 2.179",
        "puzzle_00854, 3, 2.181",
        "puzzle_00596, 3, 2.182",
        "puzzle_01855, 1, 2.182",
        "puzzle_00046, 0, 2.195",
        "puzzle_00935, 3, 2.212",
        "puzzle_01519, 1, 2.221",
        "puzzle_00399, 1, 2.233",
        "puzzle_01504, 3, 2.250",
        "puzzle_00511, 1, 2.251",
        "puzzle_00903, 3, 2.263",
        "puzzle_00993, 1, 2.265",
        "puzzle_00659, 3, 2.267",
        "puzzle_01615, 1, 2.276",
        "puzzle_00487, 3, 2.278",
        "puzzle_00915, 3, 2.285",
        "puzzle_01883, 1, 2.287",
        "puzzle_01321, 3, 2.287",
        "puzzle_00389, 1, 2.292",
        "puzzle_01771, 1, 2.299",
        "puzzle_00381, 3, 2.305",
        "puzzle_00666, 3, 2.308",
        "puzzle_00826, 3, 2.311",
        "puzzle_01798, 1, 2.312",
        "puzzle_00336, 1, 2.313",
        "puzzle_01630, 1, 2.329",
        "puzzle_00426, 1, 2.345",
        "puzzle_00022, 3, 2.348",
        "puzzle_01108, 1, 2.350",
        "puzzle_01976, 0, 2.353",
        "puzzle_00015, 1, 2.353",
        "puzzle_00045, 3, 2.361",
        "puzzle_00703, 3, 2.364",
        "puzzle_01139, 1, 2.365",
        "puzzle_00089, 1, 2.370",
        "puzzle_00351, 3, 2.372",
        "puzzle_01609, 3, 2.388",
        "puzzle_01067, 1, 2.389",
        "puzzle_00280, 1, 2.396",
        "puzzle_00952, 3, 2.397",
        "puzzle_01751, 1, 2.399",
        "puzzle_01176, 3, 2.400",
        "puzzle_01219, 1, 2.402",
        "puzzle_00517, 3, 2.403",
        "puzzle_01275, 1, 2.403",
        "puzzle_01253, 1, 2.405",
        "puzzle_00463, 1, 2.406",
        "puzzle_00615, 1, 2.411",
        "puzzle_00736, 3, 2.438",
        "puzzle_01236, 1, 2.457",
        "puzzle_01430, 1, 2.462",
        "puzzle_00345, 1, 2.465",
        "puzzle_01565, 3, 2.468",
        "puzzle_01363, 1, 2.486",
        "puzzle_00505, 1, 2.519",
        "puzzle_01520, 1, 2.527",
        "puzzle_01950, 3, 2.531",
        "puzzle_00048, 3, 2.533",
        "puzzle_00691, 2, 2.552",
        "puzzle_00043, 3, 2.555",
        "puzzle_00978, 1, 2.556",
        "puzzle_01944, 3, 2.558",
        "puzzle_01544, 1, 2.560",
        "puzzle_00832, 1, 2.562",
        "puzzle_01846, 3, 2.564",
        "puzzle_01121, 0, 2.566",
        "puzzle_00217, 3, 2.567",
        "puzzle_01557, 3, 2.597",
        "puzzle_01371, 3, 2.598",
        "puzzle_01874, 3, 2.603",
        "puzzle_01581, 1, 2.604",
        "puzzle_01390, 3, 2.611",
        "puzzle_01298, 3, 2.616",
        "puzzle_00110, 1, 2.618",
        "puzzle_00843, 1, 2.619",
        "puzzle_00053, 3, 2.619",
        "puzzle_00553, 3, 2.622",
        "puzzle_00375, 3, 2.628",
        "puzzle_01446, 3, 2.637",
        "puzzle_01809, 3, 2.644",
        "puzzle_01710, 3, 2.654",
        "puzzle_01848, 2, 2.657",
        "puzzle_01394, 3, 2.660",
        "puzzle_00646, 3, 2.662",
        "puzzle_00781, 1, 2.670",
        "puzzle_01428, 1, 2.671",
        "puzzle_00369, 2, 2.685",
        "puzzle_01877, 1, 2.695",
        "puzzle_00261, 3, 2.700",
        "puzzle_01376, 1, 2.701",
        "puzzle_01392, 1, 2.702",
        "puzzle_01797, 3, 2.707",
        "puzzle_00168, 1, 2.712",
        "puzzle_00624, 3, 2.719",
        "puzzle_00701, 3, 2.721",
        "puzzle_00943, 1, 2.725",
        "puzzle_00882, 3, 2.730",
        "puzzle_01580, 3, 2.736",
        "puzzle_00444, 3, 2.741",
        "puzzle_01585, 3, 2.761",
        "puzzle_00252, 3, 2.771",
        "puzzle_00269, 1, 2.776",
        "puzzle_00759, 3, 2.779",
        "puzzle_00625, 3, 2.783",
        "puzzle_00449, 3, 2.788",
        "puzzle_00807, 3, 2.806",
        "puzzle_00761, 1, 2.807",
        "puzzle_00981, 3, 2.820",
        "puzzle_00573, 2, 2.824",
        "puzzle_01283, 1, 2.828",
        "puzzle_00569, 2, 2.836",
        "puzzle_00234, 3, 2.839",
        "puzzle_00324, 2, 2.842",
        "puzzle_01270, 3, 2.846",
        "puzzle_00614, 3, 2.847",
        "puzzle_01664, 3, 2.847",
        "puzzle_01620, 3, 2.850",
        "puzzle_00975, 3, 2.862",
        "puzzle_01025, 3, 2.864",
        "puzzle_01431, 1, 2.866",
        "puzzle_00744, 3, 2.905",
        "puzzle_00558, 1, 2.906",
        "puzzle_00491, 0, 2.908",
        "puzzle_00216, 3, 2.912",
        "puzzle_01106, 1, 2.913",
        "puzzle_00645, 3, 2.915",
        "puzzle_00948, 3, 2.925",
        "puzzle_01947, 3, 2.934",
        "puzzle_01925, 1, 2.934",
        "puzzle_01028, 1, 2.936",
        "puzzle_01316, 1, 2.940",
        "puzzle_01802, 1, 2.945",
        "puzzle_01399, 1, 2.949",
        "puzzle_00877, 3, 2.954",
        "puzzle_01896, 1, 2.959",
        "puzzle_01708, 1, 2.968",
        "puzzle_00973, 1, 2.969",
        "puzzle_00911, 3, 2.972",
        "puzzle_01226, 3, 2.978",
        "puzzle_00748, 3, 2.985",
        "puzzle_00870, 3, 2.997",
        "puzzle_00735, 1, 2.999",
        "puzzle_01462, 3, 3.007",
        "puzzle_00241, 3, 3.013",
        "puzzle_00152, 1, 3.016",
        "puzzle_01051, 1, 3.024",
        "puzzle_01396, 3, 3.031",
        "puzzle_00361, 3, 3.042",
        "puzzle_01681, 3, 3.049",
        "puzzle_01333, 3, 3.067",
        "puzzle_00026, 1, 3.081",
        "puzzle_00397, 1, 3.084",
        "puzzle_00869, 3, 3.087",
        "puzzle_00488, 3, 3.105",
        "puzzle_01583, 3, 3.111",
        "puzzle_00821, 0, 3.112",
        "puzzle_00681, 1, 3.115",
        "puzzle_01578, 3, 3.119",
        "puzzle_01217, 1, 3.123",
        "puzzle_01628, 3, 3.134",
        "puzzle_00917, 3, 3.138",
        "puzzle_00810, 1, 3.138",
        "puzzle_00437, 1, 3.138",
        "puzzle_00642, 1, 3.140",
        "puzzle_01983, 3, 3.142",
        "puzzle_00295, 1, 3.145",
        "puzzle_00628, 1, 3.146",
        "puzzle_00967, 1, 3.162",
        "puzzle_00312, 3, 3.172",
        "puzzle_00883, 2, 3.181",
        "puzzle_01558, 1, 3.184",
        "puzzle_00510, 3, 3.188",
        "puzzle_00167, 0, 3.195",
        "puzzle_01232, 3, 3.203",
        "puzzle_01295, 3, 3.205",
        "puzzle_01908, 1, 3.212",
        "puzzle_01686, 3, 3.213",
        "puzzle_01257, 3, 3.214",
        "puzzle_01598, 1, 3.215",
        "puzzle_01529, 1, 3.220",
        "puzzle_01469, 1, 3.225",
        "puzzle_01591, 2, 3.228",
        "puzzle_00910, 1, 3.231",
        "puzzle_00825, 3, 3.239",
        "puzzle_01933, 1, 3.242",
        "puzzle_01757, 1, 3.251",
        "puzzle_00740, 1, 3.255",
        "puzzle_00031, 3, 3.271",
        "puzzle_01369, 1, 3.271",
        "puzzle_00514, 1, 3.275",
        "puzzle_00075, 3, 3.288",
        "puzzle_01624, 3, 3.295",
        "puzzle_00679, 1, 3.315",
        "puzzle_00490, 1, 3.318",
        "puzzle_01393, 3, 3.320",
        "puzzle_01707, 3, 3.322",
        "puzzle_01278, 1, 3.333",
        "puzzle_01765, 3, 3.347",
        "puzzle_00771, 3, 3.356",
        "puzzle_00058, 1, 3.360",
        "puzzle_01928, 3, 3.360",
        "puzzle_00875, 1, 3.366",
        "puzzle_00464, 1, 3.367",
        "puzzle_01963, 3, 3.379",
        "puzzle_00576, 3, 3.388",
        "puzzle_00023, 0, 3.392",
        "puzzle_01047, 1, 3.402",
        "puzzle_01775, 1, 3.402",
        "puzzle_01180, 1, 3.403",
        "puzzle_01545, 3, 3.407",
        "puzzle_00143, 1, 3.434",
        "puzzle_00099, 1, 3.434",
        "puzzle_01514, 1, 3.450",
        "puzzle_01118, 1, 3.454",
        "puzzle_00277, 1, 3.459",
        "puzzle_01395, 3, 3.464",
        "puzzle_00239, 1, 3.472",
        "puzzle_00238, 3, 3.476",
        "puzzle_00025, 3, 3.487",
        "puzzle_01869, 3, 3.492",
        "puzzle_01934, 1, 3.501",
        "puzzle_01311, 2, 3.508",
        "puzzle_01346, 3, 3.511",
        "puzzle_01812, 1, 3.511",
        "puzzle_00565, 3, 3.519",
        "puzzle_01286, 3, 3.534",
        "puzzle_00232, 0, 3.545",
        "puzzle_00195, 2, 3.549",
        "puzzle_00820, 1, 3.554",
        "puzzle_01194, 3, 3.561",
        "puzzle_00789, 1, 3.577",
        "puzzle_01905, 3, 3.578",
        "puzzle_00722, 3, 3.596",
        "puzzle_01478, 3, 3.600",
        "puzzle_01042, 3, 3.603",
        "puzzle_01331, 1, 3.606",
        "puzzle_01503, 1, 3.610",
        "puzzle_00453, 3, 3.611",
        "puzzle_00214, 3, 3.611",
        "puzzle_00732, 1, 3.612",
        "puzzle_00524, 3, 3.613",
        "puzzle_00632, 1, 3.614",
        "puzzle_00784, 3, 3.620",
        "puzzle_01082, 3, 3.622",
        "puzzle_00117, 3, 3.634",
        "puzzle_00542, 3, 3.641",
        "puzzle_00447, 1, 3.643",
        "puzzle_01367, 1, 3.645",
        "puzzle_00923, 1, 3.649",
        "puzzle_01679, 1, 3.654",
        "puzzle_01241, 1, 3.654",
        "puzzle_00551, 1, 3.659",
        "puzzle_01530, 2, 3.663",
        "puzzle_00528, 3, 3.678",
        "puzzle_01541, 3, 3.689",
        "puzzle_01032, 3, 3.697",
        "puzzle_00424, 1, 3.700",
        "puzzle_01109, 1, 3.707",
        "puzzle_01590, 3, 3.710",
        "puzzle_00259, 1, 3.714",
        "puzzle_00454, 1, 3.714",
        "puzzle_00007, 1, 3.718",
        "puzzle_01098, 3, 3.719",
        "puzzle_00579, 1, 3.721",
        "puzzle_01644, 1, 3.721",
        "puzzle_00884, 1, 3.723",
        "puzzle_00256, 1, 3.730",
        "puzzle_01442, 3, 3.735",
        "puzzle_00271, 1, 3.744",
        "puzzle_00481, 3, 3.755",
        "puzzle_01754, 1, 3.759",
        "puzzle_01153, 1, 3.773",
        "puzzle_00527, 1, 3.777",
        "puzzle_01756, 3, 3.777",
        "puzzle_00618, 3, 3.780",
        "puzzle_00706, 3, 3.805",
        "puzzle_00953, 3, 3.814",
        "puzzle_01678, 1, 3.820",
        "puzzle_01543, 3, 3.833",
        "puzzle_01473, 1, 3.864",
        "puzzle_00404, 1, 3.871",
        "puzzle_01497, 3, 3.889",
        "puzzle_00313, 3, 3.897",
        "puzzle_00125, 1, 3.900",
        "puzzle_01168, 1, 3.912",
        "puzzle_01127, 3, 3.939",
        "puzzle_00339, 1, 3.940",
        "puzzle_00149, 1, 3.944",
        "puzzle_01864, 3, 3.948",
        "puzzle_01884, 1, 3.960",
        "puzzle_00627, 3, 3.973",
        "puzzle_01986, 1, 3.973",
        "puzzle_00325, 3, 4.011",
        "puzzle_01685, 1, 4.016",
        "puzzle_01235, 1, 4.019",
        "puzzle_01501, 0, 4.023",
        "puzzle_00987, 1, 4.031",
        "puzzle_00319, 1, 4.036",
        "puzzle_00434, 1, 4.037",
        "puzzle_00060, 3, 4.078",
        "puzzle_01187, 3, 4.087",
        "puzzle_00827, 3, 4.110",
        "puzzle_00859, 1, 4.112",
        "puzzle_01368, 3, 4.122",
        "puzzle_00304, 1, 4.126",
        "puzzle_01057, 3, 4.133",
        "puzzle_00243, 3, 4.134",
        "puzzle_00405, 1, 4.134",
        "puzzle_01038, 3, 4.136",
        "puzzle_01748, 3, 4.139",
        "puzzle_01790, 3, 4.147",
        "puzzle_01875, 1, 4.157",
        "puzzle_00725, 1, 4.166",
        "puzzle_00584, 1, 4.191",
        "puzzle_01511, 3, 4.199",
        "puzzle_00019, 1, 4.203",
        "puzzle_00300, 3, 4.203",
        "puzzle_01943, 1, 4.209",
        "puzzle_00757, 1, 4.211",
        "puzzle_00589, 3, 4.212",
        "puzzle_01794, 1, 4.239",
        "puzzle_00403, 3, 4.252",
        "puzzle_01640, 1, 4.300",
        "puzzle_00860, 1, 4.303",
        "puzzle_00900, 3, 4.315",
        "puzzle_01599, 3, 4.324",
        "puzzle_01378, 1, 4.388",
        "puzzle_00640, 2, 4.389",
        "puzzle_00203, 1, 4.398",
        "puzzle_01889, 3, 4.404",
        "puzzle_01339, 3, 4.412",
        "puzzle_00181, 3, 4.442",
        "puzzle_01137, 1, 4.449",
        "puzzle_00547, 1, 4.451",
        "puzzle_01234, 1, 4.454",
        "puzzle_01528, 3, 4.457",
        "puzzle_00500, 1, 4.477",
        "puzzle_00365, 3, 4.481",
        "puzzle_00414, 3, 4.484",
        "puzzle_00617, 3, 4.501",
        "puzzle_00322, 1, 4.503",
        "puzzle_01330, 3, 4.511",
        "puzzle_00122, 3, 4.516",
        "puzzle_01437, 3, 4.526",
        "puzzle_01695, 3, 4.526",
        "puzzle_01939, 1, 4.527",
        "puzzle_00548, 1, 4.535",
        "puzzle_01917, 3, 4.542",
        "puzzle_01865, 0, 4.555",
        "puzzle_00932, 3, 4.558",
        "puzzle_01140, 1, 4.559",
        "puzzle_00590, 2, 4.566",
        "puzzle_00163, 1, 4.569",
        "puzzle_01833, 3, 4.571",
        "puzzle_00343, 0, 4.581",
        "puzzle_01505, 3, 4.596",
        "puzzle_01360, 2, 4.600",
        "puzzle_01433, 3, 4.610",
        "puzzle_01811, 3, 4.636",
        "puzzle_01237, 3, 4.652",
        "puzzle_00077, 1, 4.653",
        "puzzle_01320, 3, 4.654",
        "puzzle_01949, 3, 4.672",
        "puzzle_01242, 1, 4.672",
        "puzzle_00166, 3, 4.675",
        "puzzle_00743, 1, 4.679",
        "puzzle_00907, 3, 4.686",
        "puzzle_00945, 1, 4.694",
        "puzzle_01405, 1, 4.695",
        "puzzle_01426, 3, 4.708",
        "puzzle_01956, 3, 4.717",
        "puzzle_01953, 1, 4.723",
        "puzzle_00933, 1, 4.724",
        "puzzle_00387, 1, 4.747",
        "puzzle_00775, 1, 4.748",
        "puzzle_01289, 1, 4.753",
        "puzzle_00415, 3, 4.771",
        "puzzle_00029, 3, 4.807",
        "puzzle_01878, 1, 4.819",
        "puzzle_01830, 1, 4.824",
        "puzzle_01221, 3, 4.831",
        "puzzle_01429, 2, 4.850",
        "puzzle_00140, 1, 4.862",
        "puzzle_01255, 3, 4.873",
        "puzzle_01676, 1, 4.878",
        "puzzle_00188, 0, 4.890",
        "puzzle_01653, 3, 4.896",
        "puzzle_00079, 3, 4.915",
        "puzzle_00210, 1, 4.919",
        "puzzle_01068, 1, 4.920",
        "puzzle_00108, 1, 4.927",
        "puzzle_01709, 1, 4.945",
        "puzzle_01932, 3, 4.946",
        "puzzle_01386, 3, 4.946",
        "puzzle_00065, 3, 4.947",
        "puzzle_00938, 3, 4.947",
        "puzzle_00672, 1, 4.980",
        "puzzle_01490, 1, 4.985",
        "puzzle_01262, 1, 4.992"
      ]
    },
    {
      "Index": 3,
      "Connection": [
        "puzzle_00565, 0, 1.240",
        "puzzle_00246, 2, 1.364",
        "puzzle_00240, 0, 1.387",
        "puzzle_00313, 2, 1.454",
        "puzzle_00839, 2, 1.465",
        "puzzle_01365, 2, 1.534",
        "puzzle_01996, 2, 1.542",
        "puzzle_00463, 2, 1.573",
        "puzzle_01692, 0, 1.632",
        "puzzle_01334, 0, 1.656",
        "puzzle_00227, 2, 1.852",
        "puzzle_01329, 2, 1.872",
        "puzzle_01810, 2, 1.892",
        "puzzle_01184, 2, 1.952",
        "puzzle_00159, 2, 2.050",
        "puzzle_00557, 0, 2.053",
        "puzzle_00605, 0, 2.091",
        "puzzle_01913, 2, 2.098",
        "puzzle_01507, 2, 2.159",
        "puzzle_01644, 2, 2.171",
        "puzzle_00725, 0, 2.193",
        "puzzle_01326, 2, 2.211",
        "puzzle_01144, 0, 2.240",
        "puzzle_00375, 2, 2.269",
        "puzzle_01478, 2, 2.294",
        "puzzle_00578, 2, 2.313",
        "puzzle_01889, 0, 2.317",
        "puzzle_00275, 2, 2.359",
        "puzzle_01624, 2, 2.360",
        "puzzle_00759, 0, 2.368",
        "puzzle_01753, 0, 2.374",
        "puzzle_00438, 2, 2.414",
        "puzzle_01126, 2, 2.442",
        "puzzle_00165, 0, 2.455",
        "puzzle_01408, 0, 2.484",
        "puzzle_00568, 2, 2.487",
        "puzzle_01952, 2, 2.487",
        "puzzle_01615, 2, 2.532",
        "puzzle_00676, 0, 2.542",
        "puzzle_00791, 2, 2.634",
        "puzzle_01763, 2, 2.640",
        "puzzle_01378, 0, 2.641",
        "puzzle_01681, 2, 2.660",
        "puzzle_00458, 0, 2.672",
        "puzzle_00935, 2, 2.680",
        "puzzle_01159, 0, 2.689",
        "puzzle_01220, 2, 2.700",
        "puzzle_00511, 2, 2.718",
        "puzzle_01933, 2, 2.720",
        "puzzle_01283, 2, 2.746",
        "puzzle_01881, 2, 2.748",
        "puzzle_00248, 0, 2.757",
        "puzzle_00723, 2, 2.781",
        "puzzle_00854, 2, 2.808",
        "puzzle_01998, 0, 2.823",
        "puzzle_01223, 2, 2.826",
        "puzzle_01607, 0, 2.857",
        "puzzle_01560, 0, 2.875",
        "puzzle_01811, 2, 2.878",
        "puzzle_01257, 0, 2.880",
        "puzzle_01064, 2, 2.898",
        "puzzle_00620, 0, 2.905",
        "puzzle_00079, 2, 2.913",
        "puzzle_00681, 0, 2.927",
        "puzzle_00184, 0, 2.937",
        "puzzle_01653, 0, 2.943",
        "puzzle_00666, 0, 3.067",
        "puzzle_01219, 2, 3.089",
        "puzzle_01916, 2, 3.101",
        "puzzle_00788, 2, 3.109",
        "puzzle_01929, 2, 3.125",
        "puzzle_00231, 0, 3.138",
        "puzzle_01532, 0, 3.144",
        "puzzle_01230, 0, 3.144",
        "puzzle_01565, 2, 3.161",
        "puzzle_00514, 2, 3.175",
        "puzzle_00762, 0, 3.192",
        "puzzle_00304, 2, 3.195",
        "puzzle_00757, 2, 3.215",
        "puzzle_01822, 2, 3.231",
        "puzzle_01037, 0, 3.257",
        "puzzle_00057, 2, 3.266",
        "puzzle_01734, 0, 3.276",
        "puzzle_00330, 0, 3.281",
        "puzzle_00617, 0, 3.288",
        "puzzle_00784, 2, 3.290",
        "puzzle_00610, 2, 3.333",
        "puzzle_01490, 2, 3.367",
        "puzzle_00769, 0, 3.375",
        "puzzle_00517, 0, 3.393",
        "puzzle_01883, 0, 3.402",
        "puzzle_01809, 2, 3.424",
        "puzzle_01333, 0, 3.429",
        "puzzle_01710, 2, 3.443",
        "puzzle_00579, 0, 3.522",
        "puzzle_00665, 2, 3.559",
        "puzzle_00625, 0, 3.562",
        "puzzle_00353, 2, 3.594",
        "puzzle_01940, 2, 3.598",
        "puzzle_01317, 2, 3.600",
        "puzzle_01841, 2, 3.612",
        "puzzle_00615, 3, 3.653",
        "puzzle_00588, 2, 3.664",
        "puzzle_00399, 0, 3.671",
        "puzzle_00492, 2, 3.681",
        "puzzle_00964, 3, 3.735",
        "puzzle_00140, 2, 3.757",
        "puzzle_00455, 1, 3.768",
        "puzzle_01870, 2, 3.789",
        "puzzle_00429, 2, 3.792",
        "puzzle_00777, 1, 3.807",
        "puzzle_01917, 0, 3.836",
        "puzzle_00549, 0, 3.850",
        "puzzle_01200, 0, 3.852",
        "puzzle_00814, 2, 3.853",
        "puzzle_00827, 1, 3.862",
        "puzzle_00266, 0, 3.928",
        "puzzle_00554, 2, 3.934",
        "puzzle_01544, 0, 3.936",
        "puzzle_00649, 3, 3.938",
        "puzzle_00732, 0, 3.948",
        "puzzle_01555, 0, 3.959",
        "puzzle_00302, 2, 3.964",
        "puzzle_01309, 0, 3.969",
        "puzzle_01390, 2, 3.970",
        "puzzle_01253, 0, 3.981",
        "puzzle_01394, 0, 3.994",
        "puzzle_01373, 2, 3.998",
        "puzzle_00670, 2, 4.016",
        "puzzle_01737, 0, 4.040",
        "puzzle_01808, 2, 4.057",
        "puzzle_00466, 0, 4.057",
        "puzzle_01648, 3, 4.064",
        "puzzle_00631, 2, 4.099",
        "puzzle_00125, 0, 4.105",
        "puzzle_01181, 2, 4.105",
        "puzzle_01241, 0, 4.127",
        "puzzle_00768, 0, 4.137",
        "puzzle_01766, 0, 4.152",
        "puzzle_01338, 2, 4.154",
        "puzzle_00518, 2, 4.185",
        "puzzle_00498, 0, 4.204",
        "puzzle_00344, 3, 4.234",
        "puzzle_00970, 2, 4.240",
        "puzzle_01268, 1, 4.243",
        "puzzle_01026, 2, 4.255",
        "puzzle_00265, 0, 4.256",
        "puzzle_00016, 2, 4.259",
        "puzzle_00813, 1, 4.272",
        "puzzle_00418, 0, 4.300",
        "puzzle_01430, 2, 4.303",
        "puzzle_01985, 0, 4.305",
        "puzzle_01067, 0, 4.328",
        "puzzle_01574, 0, 4.330",
        "puzzle_01143, 0, 4.338",
        "puzzle_01484, 0, 4.344",
        "puzzle_01395, 2, 4.344",
        "puzzle_00910, 0, 4.352",
        "puzzle_01297, 0, 4.352",
        "puzzle_01209, 2, 4.387",
        "puzzle_00548, 0, 4.404",
        "puzzle_01491, 0, 4.412",
        "puzzle_01473, 0, 4.412",
        "puzzle_00488, 0, 4.435",
        "puzzle_00591, 2, 4.472",
        "puzzle_01111, 0, 4.475",
        "puzzle_01086, 1, 4.513",
        "puzzle_00722, 2, 4.520",
        "puzzle_01712, 0, 4.533",
        "puzzle_00866, 2, 4.561",
        "puzzle_01189, 0, 4.591",
        "puzzle_01108, 2, 4.593",
        "puzzle_00618, 2, 4.604",
        "puzzle_00771, 0, 4.618",
        "puzzle_00258, 0, 4.640",
        "puzzle_01871, 0, 4.649",
        "puzzle_00812, 2, 4.659",
        "puzzle_01802, 2, 4.689",
        "puzzle_00993, 0, 4.702",
        "puzzle_00440, 2, 4.703",
        "puzzle_01316, 0, 4.715",
        "puzzle_00576, 0, 4.720",
        "puzzle_00739, 2, 4.732",
        "puzzle_01210, 2, 4.759",
        "puzzle_00536, 0, 4.760",
        "puzzle_01508, 0, 4.826",
        "puzzle_01124, 2, 4.832",
        "puzzle_00690, 2, 4.837",
        "puzzle_00456, 1, 4.857",
        "puzzle_00336, 2, 4.881",
        "puzzle_01942, 0, 4.900",
        "puzzle_01778, 2, 4.915",
        "puzzle_00987, 0, 4.939",
        "puzzle_00825, 2, 4.968",
        "puzzle_01235, 0, 4.969",
        "puzzle_00619, 1, 4.985"
      ]
    }
  ]
}